aimee/__init__.py
aimee/modular.py
aimee-0.0.1.dist-info/LICENSE
aimee-0.0.1.dist-info/METADATA
aimee-0.0.1.dist-info/WHEEL
aimee-0.0.1.dist-info/top_level.txt
aimee-0.0.1.dist-info/RECORD
